<?xml version="1.0" encoding="UTF-8"?>
<FasigTiptonSalesServices>
<Service>saleUpdates</Service>
<FasigTiptonUpdates>
	<Update>
+    .  **=Fanditha (IRE)** (2006 f. by =Danehill Dancer (IRE)). 4 wins, 2 to 5, 40,385 Pounds, in England, 2nd E.B.F. Kheleyf Hoppings S. [L]; unplaced in 1 start in France; unplaced in 1 start in Ireland; unplaced in 2 starts in United Arab Emirates. (Total: $66,009). Dam of 7 foals, 4 to race, 4 winners--
		<hip>134</hip>
		<SaleEntryCode>PH23</SaleEntryCode>
		<SaleCode>FTFEB</SaleCode>
		<SaleName>FT FEB MIXED 21</SaleName>
		<HorseName>**=Fanditha</HorseName>
		<HorseYOB>2006</HorseYOB>
		<HorseSex>f</HorseSex>
		<DamName>Splendid</DamName>
+    .  .  =Kentucky Hardboot (IRE) (2017 g. by Starspangledbanner (AUS)). Winner at 3 and 4, 15,699 Pounds, in England. (Total: $21,018).
		<hip>134</hip>
		<SaleEntryCode>PH23</SaleEntryCode>
		<SaleCode>FTFEB</SaleCode>
		<SaleName>FT FEB MIXED 21</SaleName>
		<HorseName>=Kentucky Hardboot</HorseName>
		<HorseYOB>2017</HorseYOB>
		<HorseSex>c</HorseSex>
+    .  .  =Cuppatee (IRE) (2013 f. by =Canford Cliffs (IRE)). 2 wins at 2, 10,871 Pounds, in England. (Total: $16,444). Died 2019. Dam of 2 foals, 1 to race--
		<hip>134</hip>
		<SaleEntryCode>PH23</SaleEntryCode>
		<SaleCode>FTFEB</SaleCode>
		<SaleName>FT FEB MIXED 21</SaleName>
		<HorseName>=Cuppatee</HorseName>
		<HorseYOB>2013</HorseYOB>
		<HorseSex>f</HorseSex>
+    .  .  =Cosmogyral (IRE) (2015 f. by =Camelot (GB)). Winner at 4, 6,777 Pounds, in England. (Total: $8,703). Dam of 3 foals, 1 to race--
		<hip>134</hip>
		<SaleEntryCode>PH23</SaleEntryCode>
		<SaleCode>FTFEB</SaleCode>
		<SaleName>FT FEB MIXED 21</SaleName>
		<HorseName>=Cosmogyral</HorseName>
		<HorseYOB>2015</HorseYOB>
		<HorseSex>g</HorseSex>
+    .  .  =Jungle Warfare (IRE) (2016 g. by =Bungle Inthejungle (GB)). Winner at 3, 35,014 Krona, in Sweden; unplaced in England. (Total: $3,653).
		<hip>134</hip>
		<SaleEntryCode>PH23</SaleEntryCode>
		<SaleCode>FTFEB</SaleCode>
		<SaleName>FT FEB MIXED 21</SaleName>
		<HorseName>=Jungle Warfare</HorseName>
		<HorseYOB>2016</HorseYOB>
		<HorseSex>g</HorseSex>
+    .  =Lavish (IRE) (2015 f. by =Camelot (GB)). Unraced in Ireland. Dam of 2 foals, 1 to race, 1 winner--
		<hip>134</hip>
		<SaleEntryCode>PH23</SaleEntryCode>
		<SaleCode>FTFEB</SaleCode>
		<SaleName>FT FEB MIXED 21</SaleName>
		<HorseName>=Lavish</HorseName>
		<HorseYOB>2015</HorseYOB>
		<HorseSex>f</HorseSex>
		<DamName>Splendid</DamName>
+    .  .  =Leibovitz (IRE) (2020 f. by Starspangledbanner (AUS)). Winner in 2 starts at 2, 2022, 13,500 Euro, in France. (Total: $13,145).
		<hip>134</hip>
		<SaleEntryCode>PH23</SaleEntryCode>
		<SaleCode>FTFEB</SaleCode>
		<SaleName>FT FEB MIXED 21</SaleName>
		<HorseName>=Leibovitz</HorseName>
		<HorseYOB>2020</HorseYOB>
		<HorseSex>f</HorseSex>
+    .  =Simply The Best (TUR) (2003 f. by Sri Pekan). Unraced in Turkey. Dam of 3 foals, 1 to race--
		<hip>134</hip>
		<SaleEntryCode>PH23</SaleEntryCode>
		<SaleCode>FTFEB</SaleCode>
		<SaleName>FT FEB MIXED 21</SaleName>
		<HorseName>=Simply The Best</HorseName>
		<HorseYOB>2003</HorseYOB>
		<HorseSex>f</HorseSex>
		<DamName>=Sadler's Fly</DamName>
+    .  =Kiss Of Fire (TUR) (2007 f. by Eagle Eyed). Unplaced in 2 starts in Turkey. Dam of 1 foal--
		<hip>134</hip>
		<SaleEntryCode>PH23</SaleEntryCode>
		<SaleCode>FTFEB</SaleCode>
		<SaleName>FT FEB MIXED 21</SaleName>
		<HorseName>=Kiss Of Fire</HorseName>
		<HorseYOB>2007</HorseYOB>
		<HorseSex>f</HorseSex>
		<DamName>=Sadler's Fly</DamName>
	</update>
</FasigTiptonUpdates>
</FasigTiptonSalesServices>