<?xml version="1.0" encoding="UTF-8"?>
<FasigTiptonSalesServices>
<Service>saleUpdates</Service>
<FasigTiptonUpdates>
	<Update>
+    **KAVOD** (2019 c. by Lea). 4 wins at 2 and 3, placed at 4, 2023, $540,240, 1st Advent S. (OP, $90,000), 2nd Tremont S. [L] (BEL, $30,000), Ring The Bell S. (OP, $28,650).
		Gen 2
		<hip>182</hip>
		<SaleEntryCode>PH23</SaleEntryCode>
		<SaleCode>FTFEB</SaleCode>
		<SaleName>FT FEB MIXED 21</SaleName>
		<HorseName></HorseName>
		<HorseYOB>2019</HorseYOB>
		<HorseSex></HorseSex>
		<DamName>WEEKEND CONNECTION</DamName>
		<DamDamName></DamDamName>
		<SireName></SireName>
		<OfficialPosition></OfficialPosition>
		<RaceNumber></RaceNumber>
		<RaceType></RaceType>
		<Grade></Grade>
		<RaceDate></RaceDate>
		<TrackName></TrackName>
		<UpdPosition></UpdPosition>
		<Generation></Generation>
		<Earnings></Earnings>
		<BlackType></BlackType>
		<WhiteType></WhiteType>
		<UpdateLink>http://www.test.equineline.com/to/be/determined/00182.htm</UpdateLink>
+    .  Another Hot Mess (2019 f. by Hard Spun). 3 wins in 6 starts at 3 and 4, 2023, $79,350.
Found Gen 3
		<hip>182</hip>
		<SaleEntryCode>PH23</SaleEntryCode>
		<SaleCode>FTFEB</SaleCode>
		<SaleName>FT FEB MIXED 21</SaleName>
		<HorseName></HorseName>
		<HorseYOB>2019</HorseYOB>
		<HorseSex></HorseSex>
		<DamName></DamName>
		<DamDamName></DamDamName>
		<SireName></SireName>
		<OfficialPosition></OfficialPosition>
		<RaceNumber></RaceNumber>
		<RaceType></RaceType>
		<Grade></Grade>
		<RaceDate></RaceDate>
		<TrackName></TrackName>
		<UpdPosition></UpdPosition>
		<Generation></Generation>
		<Earnings></Earnings>
		<BlackType></BlackType>
		<WhiteType></WhiteType>
		<UpdateLink>http://www.test.equineline.com/to/be/determined/00182.htm</UpdateLink>
	</update>
</FasigTiptonUpdates>
</FasigTiptonSalesServices>