<?xml version="1.0" encoding="UTF-8"?>
<FasigTiptonSalesServices>
<Service>saleUpdates</Service>
<FasigTiptonUpdates>
	<Update>
+    Angkor (2018 g. by Anchor Down). Winner at 2, placed at 4, 2022, $156,683.
		<hip>427</hip>
		<SaleEntryCode>PH23</SaleEntryCode>
		<SaleCode>FTFEB</SaleCode>
		<SaleName>FT FEB MIXED 21</SaleName>
		<HorseName>Angkor</HorseName>
		<HorseYOB>2018</HorseYOB>
		<HorseSex>g</HorseSex>
		<DamDamName>**Afleet Lover**</DamDamName>
		<SireName>n</SireName>
		<OfficalPosition>3</OfficalPosition>
		<RaceNumber>2</RaceNumber>
		<RaceType>MCL</RaceType>
		<Grade></Grade>
		<RaceDate>20200606</RaceDate>
		<TrackName>CHURCHILL DOWNS</TrackName>
		<UpdPosition>2</UpdPosition>
		<Generation>2</Generation>
		<Earnings>$2,200</Earnings>
		<BlackType>N</BlackType>
		<WhiteType>Y</WhiteType>
		<UpdateLink>http://www.test.equineline.com/to/be/determined/00003.htm</UpdateLink>
update on line 40: +    Angkor (2018 g. by Anchor Down). Winner at 2, placed at 4, 2022, $156,683.
Dam is in line 36:   **Afleet Lover**, by Northern Afleet. 5 wins at 3 and 4, $104,471, 3rd Hawkeyes H.-R (PRM, $7,500). Dam of 7 foals, 6 to race, 5 winners--
+    Graydawn Day (2017 f. by Graydar). Winner at 4, placed at 5, 2022, $27,211.
		<hip>427</hip>
		<SaleEntryCode>PH23</SaleEntryCode>
		<SaleCode>FTFEB</SaleCode>
		<SaleName>FT FEB MIXED 21</SaleName>
		<HorseName>Graydawn Day</HorseName>
		<HorseYOB>2017</HorseYOB>
		<HorseSex>r</HorseSex>
		<DamDamName>**Afleet Lover**</DamDamName>
		<SireName>r</SireName>
		<OfficalPosition>3</OfficalPosition>
		<RaceNumber>2</RaceNumber>
		<RaceType>MCL</RaceType>
		<Grade></Grade>
		<RaceDate>20200606</RaceDate>
		<TrackName>CHURCHILL DOWNS</TrackName>
		<UpdPosition>2</UpdPosition>
		<Generation>2</Generation>
		<Earnings>$2,200</Earnings>
		<BlackType>N</BlackType>
		<WhiteType>Y</WhiteType>
		<UpdateLink>http://www.test.equineline.com/to/be/determined/00003.htm</UpdateLink>
update on line 46: +    Graydawn Day (2017 f. by Graydar). Winner at 4, placed at 5, 2022, $27,211.
Dam is in line 36:   **Afleet Lover**, by Northern Afleet. 5 wins at 3 and 4, $104,471, 3rd Hawkeyes H.-R (PRM, $7,500). Dam of 7 foals, 6 to race, 5 winners--
	</update>
</FasigTiptonUpdates>
</FasigTiptonSalesServices>