<?xml version="1.0" encoding="UTF-8"?>
<FasigTiptonSalesServices>
<Service>saleUpdates</Service>
<FasigTiptonUpdates>
	<Update>
+    .  Wound Up (2020 c. by Mendelssohn). Winner at 2, 2022, $75,270.
Found Gen 3
		<hip>469</hip>
		<SaleEntryCode>PH23</SaleEntryCode>
		<SaleCode>FTFEB</SaleCode>
		<SaleName>FT FEB MIXED 21</SaleName>
		<HorseName></HorseName>
		<HorseYOB>2020</HorseYOB>
		<HorseSex></HorseSex>
		<DamName></DamName>
		<DamDamName></DamDamName>
		<SireName></SireName>
		<OfficialPosition></OfficialPosition>
		<RaceNumber></RaceNumber>
		<RaceType></RaceType>
		<Grade></Grade>
		<RaceDate></RaceDate>
		<TrackName></TrackName>
		<UpdPosition></UpdPosition>
		<Generation></Generation>
		<Earnings></Earnings>
		<BlackType></BlackType>
		<WhiteType></WhiteType>
		<UpdateLink>http://www.test.equineline.com/to/be/determined/00469.htm</UpdateLink>
+    .  .  Emblem Time (2018 c. by Not This Time). Winner at 2 and 4, 2022, 242,250 Riyals, in Saudi Arabia. Sent from United States to Saudi Arabia in 2020. (Total: $64,599).
Found Gen 4
		<hip>469</hip>
		<SaleEntryCode>PH23</SaleEntryCode>
		<SaleCode>FTFEB</SaleCode>
		<SaleName>FT FEB MIXED 21</SaleName>
		<HorseName></HorseName>
		<HorseYOB>2018</HorseYOB>
		<HorseSex></HorseSex>
		<DamName></DamName>
		<DamDamName></DamDamName>
		<SireName></SireName>
		<OfficialPosition></OfficialPosition>
		<RaceNumber></RaceNumber>
		<RaceType></RaceType>
		<Grade></Grade>
		<RaceDate></RaceDate>
		<TrackName></TrackName>
		<UpdPosition></UpdPosition>
		<Generation></Generation>
		<Earnings></Earnings>
		<BlackType></BlackType>
		<WhiteType></WhiteType>
		<UpdateLink>http://www.test.equineline.com/to/be/determined/00469.htm</UpdateLink>
+    .  .  Roz (2019 f. by Fed Biz). 2 wins at 3, 2022, $52,730.
Found Gen 4
		<hip>469</hip>
		<SaleEntryCode>PH23</SaleEntryCode>
		<SaleCode>FTFEB</SaleCode>
		<SaleName>FT FEB MIXED 21</SaleName>
		<HorseName></HorseName>
		<HorseYOB>2019</HorseYOB>
		<HorseSex></HorseSex>
		<DamName></DamName>
		<DamDamName></DamDamName>
		<SireName></SireName>
		<OfficialPosition></OfficialPosition>
		<RaceNumber></RaceNumber>
		<RaceType></RaceType>
		<Grade></Grade>
		<RaceDate></RaceDate>
		<TrackName></TrackName>
		<UpdPosition></UpdPosition>
		<Generation></Generation>
		<Earnings></Earnings>
		<BlackType></BlackType>
		<WhiteType></WhiteType>
		<UpdateLink>http://www.test.equineline.com/to/be/determined/00469.htm</UpdateLink>
+    .  .  Glacken's Cause (2019 f. by Creative Cause). 3 wins at 3, 2022, $60,805.
Found Gen 4
		<hip>469</hip>
		<SaleEntryCode>PH23</SaleEntryCode>
		<SaleCode>FTFEB</SaleCode>
		<SaleName>FT FEB MIXED 21</SaleName>
		<HorseName></HorseName>
		<HorseYOB>2019</HorseYOB>
		<HorseSex></HorseSex>
		<DamName></DamName>
		<DamDamName></DamDamName>
		<SireName></SireName>
		<OfficialPosition></OfficialPosition>
		<RaceNumber></RaceNumber>
		<RaceType></RaceType>
		<Grade></Grade>
		<RaceDate></RaceDate>
		<TrackName></TrackName>
		<UpdPosition></UpdPosition>
		<Generation></Generation>
		<Earnings></Earnings>
		<BlackType></BlackType>
		<WhiteType></WhiteType>
		<UpdateLink>http://www.test.equineline.com/to/be/determined/00469.htm</UpdateLink>
+    .  .  .  Indian Empire (2019 g. by Bodemeister). 5 wins at 3, 2022, $65,766.
		<hip>469</hip>
		<SaleEntryCode>PH23</SaleEntryCode>
		<SaleCode>FTFEB</SaleCode>
		<SaleName>FT FEB MIXED 21</SaleName>
		<HorseName>+    .  .  .  Indian Empire (</HorseName>
		<HorseYOB>2019</HorseYOB>
		<HorseSex></HorseSex>
		<DamName></DamName>
		<DamDamName></DamDamName>
		<SireName></SireName>
		<OfficialPosition></OfficialPosition>
		<RaceNumber></RaceNumber>
		<RaceType></RaceType>
		<Grade></Grade>
		<RaceDate></RaceDate>
		<TrackName></TrackName>
		<UpdPosition></UpdPosition>
		<Generation></Generation>
		<Earnings></Earnings>
		<BlackType></BlackType>
		<WhiteType></WhiteType>
		<UpdateLink>http://www.test.equineline.com/to/be/determined/00469.htm</UpdateLink>
+    .  .  Summer Sunset (2019 g. by Summer Front). 2 wins at 3, 2022, $72,367, in Canada. (Total: $56,994).
Found Gen 4
		<hip>469</hip>
		<SaleEntryCode>PH23</SaleEntryCode>
		<SaleCode>FTFEB</SaleCode>
		<SaleName>FT FEB MIXED 21</SaleName>
		<HorseName></HorseName>
		<HorseYOB>2019</HorseYOB>
		<HorseSex></HorseSex>
		<DamName></DamName>
		<DamDamName></DamDamName>
		<SireName></SireName>
		<OfficialPosition></OfficialPosition>
		<RaceNumber></RaceNumber>
		<RaceType></RaceType>
		<Grade></Grade>
		<RaceDate></RaceDate>
		<TrackName></TrackName>
		<UpdPosition></UpdPosition>
		<Generation></Generation>
		<Earnings></Earnings>
		<BlackType></BlackType>
		<WhiteType></WhiteType>
		<UpdateLink>http://www.test.equineline.com/to/be/determined/00469.htm</UpdateLink>
+    .  .  Alonzo Mosely (2017 g. by Tonalist). Winner at 4, placed at 5, 2022, $61,080.
Found Gen 4
		<hip>469</hip>
		<SaleEntryCode>PH23</SaleEntryCode>
		<SaleCode>FTFEB</SaleCode>
		<SaleName>FT FEB MIXED 21</SaleName>
		<HorseName></HorseName>
		<HorseYOB>2017</HorseYOB>
		<HorseSex></HorseSex>
		<DamName></DamName>
		<DamDamName></DamDamName>
		<SireName></SireName>
		<OfficialPosition></OfficialPosition>
		<RaceNumber></RaceNumber>
		<RaceType></RaceType>
		<Grade></Grade>
		<RaceDate></RaceDate>
		<TrackName></TrackName>
		<UpdPosition></UpdPosition>
		<Generation></Generation>
		<Earnings></Earnings>
		<BlackType></BlackType>
		<WhiteType></WhiteType>
		<UpdateLink>http://www.test.equineline.com/to/be/determined/00469.htm</UpdateLink>
	</update>
</FasigTiptonUpdates>
</FasigTiptonSalesServices>