<?xml version="1.0" encoding="UTF-8"?>
<FasigTiptonSalesServices>
<Service>saleUpdates</Service>
<FasigTiptonUpdates>
	<Update>
		<hip>499</hip>
		<SaleEntryCode>PH23</SaleEntryCode>
		<SaleCode>FTFEB</SaleCode>
		<SaleName>FT FEB MIXED 21</SaleName>
		<HorseName>Dakine Dancer</HorseName>
		<HorseYOB>2014 </HorseYOB>
		<HorseSex>c</HorseSex>
		<hip>499</hip>
		<SaleEntryCode>PH23</SaleEntryCode>
		<SaleCode>FTFEB</SaleCode>
		<SaleName>FT FEB MIXED 21</SaleName>
		<HorseName>God's Force</HorseName>
		<HorseYOB>2018 </HorseYOB>
		<HorseSex>r</HorseSex>
		<hip>499</hip>
		<SaleEntryCode>PH23</SaleEntryCode>
		<SaleCode>FTFEB</SaleCode>
		<SaleName>FT FEB MIXED 21</SaleName>
		<HorseName>**Hot Fun**</HorseName>
		<HorseYOB>2010 </HorseYOB>
		<HorseSex>f</HorseSex>
		<hip>499</hip>
		<SaleEntryCode>PH23</SaleEntryCode>
		<SaleCode>FTFEB</SaleCode>
		<SaleName>FT FEB MIXED 21</SaleName>
		<HorseName>Wicked Hot</HorseName>
		<HorseYOB>2018 </HorseYOB>
		<HorseSex>c</HorseSex>
		<hip>499</hip>
		<SaleEntryCode>PH23</SaleEntryCode>
		<SaleCode>FTFEB</SaleCode>
		<SaleName>FT FEB MIXED 21</SaleName>
		<HorseName>Ridgelysredhot</HorseName>
		<HorseYOB>2017 </HorseYOB>
		<HorseSex>g</HorseSex>
		<hip>499</hip>
		<SaleEntryCode>PH23</SaleEntryCode>
		<SaleCode>FTFEB</SaleCode>
		<SaleName>FT FEB MIXED 21</SaleName>
		<HorseName>Hot Spice</HorseName>
		<HorseYOB>2019 </HorseYOB>
		<HorseSex>c</HorseSex>
		<hip>499</hip>
		<SaleEntryCode>PH23</SaleEntryCode>
		<SaleCode>FTFEB</SaleCode>
		<SaleName>FT FEB MIXED 21</SaleName>
		<HorseName>Hot Promise</HorseName>
		<HorseYOB>2022 </HorseYOB>
		<HorseSex>r</HorseSex>
		<hip>499</hip>
		<SaleEntryCode>PH23</SaleEntryCode>
		<SaleCode>FTFEB</SaleCode>
		<SaleName>FT FEB MIXED 21</SaleName>
		<HorseName>Mon Gateau</HorseName>
		<HorseYOB>2021 </HorseYOB>
		<HorseSex>g</HorseSex>
		<hip>499</hip>
		<SaleEntryCode>PH23</SaleEntryCode>
		<SaleCode>FTFEB</SaleCode>
		<SaleName>FT FEB MIXED 21</SaleName>
		<HorseName>Fun Notion</HorseName>
		<HorseYOB>2020 </HorseYOB>
		<HorseSex>g</HorseSex>
		<hip>499</hip>
		<SaleEntryCode>PH23</SaleEntryCode>
		<SaleCode>FTFEB</SaleCode>
		<SaleName>FT FEB MIXED 21</SaleName>
		<HorseName>**E Dubai's Humor**</HorseName>
		<HorseYOB>2012 </HorseYOB>
		<HorseSex>r</HorseSex>
		<hip>499</hip>
		<SaleEntryCode>PH23</SaleEntryCode>
		<SaleCode>FTFEB</SaleCode>
		<SaleName>FT FEB MIXED 21</SaleName>
		<HorseName>Badger Tooth</HorseName>
		<HorseYOB>2018 </HorseYOB>
		<HorseSex>g</HorseSex>
		<hip>499</hip>
		<SaleEntryCode>PH23</SaleEntryCode>
		<SaleCode>FTFEB</SaleCode>
		<SaleName>FT FEB MIXED 21</SaleName>
		<HorseName>Wickeddivine</HorseName>
		<HorseYOB>2022 </HorseYOB>
		<HorseSex>c</HorseSex>
		<hip>499</hip>
		<SaleEntryCode>PH23</SaleEntryCode>
		<SaleCode>FTFEB</SaleCode>
		<SaleName>FT FEB MIXED 21</SaleName>
		<HorseName>Unnamed</HorseName>
		<HorseYOB>2021 </HorseYOB>
		<HorseSex>g</HorseSex>
		<hip>499</hip>
		<SaleEntryCode>PH23</SaleEntryCode>
		<SaleCode>FTFEB</SaleCode>
		<SaleName>FT FEB MIXED 21</SaleName>
		<HorseName>Finaljump</HorseName>
		<HorseYOB>2020 </HorseYOB>
		<HorseSex>f</HorseSex>
	</update>
</FasigTiptonUpdates>
</FasigTiptonSalesServices>