<?xml version="1.0" encoding="UTF-8"?>
<FasigTiptonSalesServices>
<Service>saleUpdates</Service>
<FasigTiptonUpdates>
	<Update>
		<hip>80</hip>
		<SaleEntryCode>PH23</SaleEntryCode>
		<SaleCode>FTFEB</SaleCode>
		<SaleName>FT FEB MIXED 21</SaleName>
		<HorseName>Cindy's G Man</HorseName>
		<HorseYOB>2019 </HorseYOB>
		<HorseSex>g</HorseSex>
		<DamName>My Little Darlings</DamName>
		<hip>80</hip>
		<SaleEntryCode>PH23</SaleEntryCode>
		<SaleCode>FTFEB</SaleCode>
		<SaleName>FT FEB MIXED 21</SaleName>
		<HorseName>Brit's Wit</HorseName>
		<HorseYOB>2019 </HorseYOB>
		<HorseSex>r</HorseSex>
36
		<DamDamName>SECRET HUMOR</DamDamName>
		<SireName>Sire Name</SireName>
		<OfficalPosition>3</OfficalPosition>
		<RaceNumber>2</RaceNumber>
		<RaceType>MCL</RaceType>
		<Grade></Grade>
		<RaceDate>20200606</RaceDate>
		<TrackName>CHURCHILL DOWNS</TrackName>
		<UpdPosition>2</UpdPosition>
<Generation>2</Generation>
<Earnings>$2,200</Earnings>
<BlackType>N</BlackType>
<WhiteType>Y</WhiteType>
<UpdateLink>http://www.test.equineline.com/to/be/determined/00003.htm</UpdateLink>
update on line 49: +    Brit's Wit (2019 g. by English Channel). Winner at 2 and 3, 2022, $66,331.
Dam is in line 36:   SECRET HUMOR, by Yes It's True. Winner at 3, $11,364. Half-sister to **KAZOO** ($637,000, 1st Toboggan H. **[G3]** (AQU, $64,440), etc., sire), **Lemon Cream Pie** ($150,858, 2nd Knickerbocker S. **[G3]** (BEL, $21,300)), **Daddy Joe** ($263,304, 2nd Rushaway S. [L] (TP, $20,000)). Dam of 9 foals, 7 to race, 7 winners--
	</update>
</FasigTiptonUpdates>
</FasigTiptonSalesServices>